django/__init__.py
django/pydantic/__init__.py
django/pydantic/decorators.py
django_pydantic_core-1.0.0.dist-info/METADATA
django_pydantic_core-1.0.0.dist-info/WHEEL
django_pydantic_core-1.0.0.dist-info/top_level.txt
django_pydantic_core-1.0.0.dist-info/RECORD
